kkroot/canvas.py
kkroot/style.py
kkroot-0.0.3.dist-info/LICENSE
kkroot-0.0.3.dist-info/METADATA
kkroot-0.0.3.dist-info/WHEEL
kkroot-0.0.3.dist-info/top_level.txt
kkroot-0.0.3.dist-info/RECORD
