Metadata-Version: 2.1
Name: kkroot
Version: 0.0.3
Summary: Helpful functions for making pretty ROOT plots.
Home-page: https://github.com/kkrizka/kkroot
Author: Karol Krizka
Author-email: kkrizka@gmail.com
Classifier: Programming Language :: Python :: 3
Classifier: License :: OSI Approved :: GNU General Public License v3 (GPLv3)
Classifier: Operating System :: OS Independent
License-File: LICENSE
